supsim/__init__.py
supsim/__main__.py
supsim/rand_poly.py
supsim/supsim.py
supsim/util.py
supsim-0.1.3.dist-info/LICENSE
supsim-0.1.3.dist-info/METADATA
supsim-0.1.3.dist-info/WHEEL
supsim-0.1.3.dist-info/entry_points.txt
supsim-0.1.3.dist-info/top_level.txt
supsim-0.1.3.dist-info/RECORD
