Metadata-Version: 2.1
Name: supsim
Version: 0.1.3
Summary: A software developed for studying two-predictor suppressor effects via computerized simulations
Home-page: https://supsim.netlify.app
Author: Morteza Nazifi and Hamid Fadishei
Author-email: fadishei@yahoo.com
License: GPLv3+
Keywords: regression,suppression
Platform: UNKNOWN
Classifier: Development Status :: 5 - Production/Stable
Classifier: Environment :: Console
Classifier: Intended Audience :: Science/Research
Classifier: License :: OSI Approved :: GNU General Public License v3 or later (GPLv3+)
Classifier: Natural Language :: English
Classifier: Operating System :: OS Independent
Classifier: Programming Language :: Python
Classifier: Programming Language :: Python :: 3
Classifier: Topic :: Scientific/Engineering :: Mathematics
Requires-Python: >=3.6
Requires-Dist: numpy (>=1.18.5)
Requires-Dist: pandas (>=1.0.4)
Requires-Dist: scikit-learn (>=0.23.1)
Requires-Dist: matplotlib (>=3.2.1)
Requires-Dist: openpyxl (>=2.4.11)
Requires-Dist: tqdm (>=4.45.0)
